odoo/addons/account_cash_invoice/README.rst
odoo/addons/account_cash_invoice/__init__.py
odoo/addons/account_cash_invoice/__manifest__.py
odoo/addons/account_cash_invoice/i18n/account_cash_invoice.pot
odoo/addons/account_cash_invoice/i18n/hr.po
odoo/addons/account_cash_invoice/i18n/pt.po
odoo/addons/account_cash_invoice/models/__init__.py
odoo/addons/account_cash_invoice/models/account_bank_statement_line.py
odoo/addons/account_cash_invoice/readme/CONTRIBUTORS.rst
odoo/addons/account_cash_invoice/readme/DESCRIPTION.rst
odoo/addons/account_cash_invoice/readme/ROADMAP.rst
odoo/addons/account_cash_invoice/readme/USAGE.rst
odoo/addons/account_cash_invoice/static/description/icon.png
odoo/addons/account_cash_invoice/static/description/index.html
odoo/addons/account_cash_invoice/tests/__init__.py
odoo/addons/account_cash_invoice/tests/test_pay_invoice.py
odoo/addons/account_cash_invoice/wizard/__init__.py
odoo/addons/account_cash_invoice/wizard/cash_invoice_in.py
odoo/addons/account_cash_invoice/wizard/cash_invoice_in.xml
odoo/addons/account_cash_invoice/wizard/cash_invoice_out.py
odoo/addons/account_cash_invoice/wizard/cash_invoice_out.xml
odoo12_addon_account_cash_invoice-12.0.1.1.0.dist-info/METADATA
odoo12_addon_account_cash_invoice-12.0.1.1.0.dist-info/WHEEL
odoo12_addon_account_cash_invoice-12.0.1.1.0.dist-info/top_level.txt
odoo12_addon_account_cash_invoice-12.0.1.1.0.dist-info/RECORD
